ufcstats/__init__.py
ufcstats/ufcstats.py
ufcstats-0.0.3.dist-info/LICENSE.txt
ufcstats-0.0.3.dist-info/METADATA
ufcstats-0.0.3.dist-info/WHEEL
ufcstats-0.0.3.dist-info/top_level.txt
ufcstats-0.0.3.dist-info/RECORD
