Metadata-Version: 2.1
Name: ufcstats
Version: 0.0.3
Summary: A package to retrieve stats from ufcstats.com
Home-page: https://github.com/AshankKumar/UFCStats
Author: Ashank Kumar
Author-email: ashankkumar01@gmail.com
License: UNKNOWN
Platform: UNKNOWN
Classifier: Programming Language :: Python :: 3
Classifier: License :: OSI Approved :: MIT License
Classifier: Operating System :: OS Independent
